mseep_notebookllama-0.4.1.dist-info/licenses/LICENSE
notebookllama/Home.py
notebookllama/__init__.py
notebookllama/audio.py
notebookllama/documents.py
notebookllama/instrumentation.py
notebookllama/mindmap.py
notebookllama/models.py
notebookllama/processing.py
notebookllama/querying.py
notebookllama/server.py
notebookllama/utils.py
notebookllama/verifying.py
notebookllama/workflow.py
notebookllama/pages/1_Document_Management_UI.py
notebookllama/pages/2_Document_Chat.py
notebookllama/pages/3_Interactive_Table_and_Plot_Visualization.py
notebookllama/pages/4_Observability_Dashboard.py
mseep_notebookllama-0.4.1.dist-info/METADATA
mseep_notebookllama-0.4.1.dist-info/WHEEL
mseep_notebookllama-0.4.1.dist-info/top_level.txt
mseep_notebookllama-0.4.1.dist-info/RECORD
