Metadata-Version: 2.4
Name: mseep-notebookllama
Version: 0.4.1
Summary: An OSS and LlamaCloud-backed alternative to NotebookLM
Author-email: mseep <support@skydeck.ai>
Requires-Python: >=3.13
License-File: LICENSE
Requires-Dist: audioop-lts>=0.2.1
Requires-Dist: elevenlabs>=2.5.0
Requires-Dist: fastmcp>=2.9.2
Requires-Dist: ffprobe>=0.5
Requires-Dist: llama-cloud>=0.1.29
Requires-Dist: llama-cloud-services>=0.6.38
Requires-Dist: llama-index-core>=0.12.44
Requires-Dist: llama-index-embeddings-azure-inference>=0.3.0
Requires-Dist: llama-index-embeddings-bedrock>=0.5.2
Requires-Dist: llama-index-embeddings-cohere>=0.5.1
Requires-Dist: llama-index-embeddings-gemini>=0.3.2
Requires-Dist: llama-index-embeddings-huggingface-api>=0.3.1
Requires-Dist: llama-index-embeddings-openai>=0.3.1
Requires-Dist: llama-index-indices-managed-llama-cloud>=0.6.11
Requires-Dist: llama-index-llms-openai>=0.4.7
Requires-Dist: llama-index-observability-otel>=0.1.1
Requires-Dist: llama-index-tools-mcp>=0.2.5
Requires-Dist: llama-index-workflows>=1.0.1
Requires-Dist: markdown-analysis>=0.1.5
Requires-Dist: mypy>=1.16.1
Requires-Dist: opentelemetry-exporter-otlp-proto-http>=1.34.1
Requires-Dist: plotly>=6.2.0
Requires-Dist: pre-commit>=4.2.0
Requires-Dist: psycopg2-binary>=2.9.10
Requires-Dist: pydub>=0.25.1
Requires-Dist: pytest>=8.4.1
Requires-Dist: pytest-asyncio>=1.0.0
Requires-Dist: python-dotenv>=1.1.1
Requires-Dist: pyvis>=0.3.2
Requires-Dist: randomname>=0.2.1
Requires-Dist: streamlit>=1.46.1
Requires-Dist: textual>=3.7.1
Dynamic: license-file
